python_freeathome_local/__init__.py
python_freeathome_local/__version__.py
python_freeathome_local/exceptions.py
python_freeathome_local/freeathome.py
python_freeathome_local/functionids.py
python_freeathome_local/pairingids.py
python_freeathome_local/parameterids.py
python_freeathome_local/py.typed
python_freeathome_local/models/__init__.py
python_freeathome_local/models/abstractchannel.py
python_freeathome_local/models/abstractdatapoint.py
python_freeathome_local/models/abstractdevice.py
python_freeathome_local/models/abstractparameter.py
python_freeathome_local/models/blindsensorchannel.py
python_freeathome_local/models/brightnesssensorchannel.py
python_freeathome_local/models/channelfactory.py
python_freeathome_local/models/datapointfactory.py
python_freeathome_local/models/desdoorringingsensorchannel.py
python_freeathome_local/models/devicefactory.py
python_freeathome_local/models/floor.py
python_freeathome_local/models/floorplan.py
python_freeathome_local/models/forceonoffsensorchannel.py
python_freeathome_local/models/inputdatapoint.py
python_freeathome_local/models/movementdetectorchannel.py
python_freeathome_local/models/outputdatapoint.py
python_freeathome_local/models/parameter.py
python_freeathome_local/models/parameterfactory.py
python_freeathome_local/models/rainsensorchannel.py
python_freeathome_local/models/room.py
python_freeathome_local/models/switchactuatorchannel.py
python_freeathome_local/models/switchsensorchannel.py
python_freeathome_local/models/sysap.py
python_freeathome_local/models/temperaturesensorchannel.py
python_freeathome_local/models/tpdevice.py
python_freeathome_local/models/triggerchannel.py
python_freeathome_local/models/windowdoorsensorchannel.py
python_freeathome_local/models/windsensorchannel.py
python_freeathome_local-0.0.6.dist-info/LICENSE
python_freeathome_local-0.0.6.dist-info/METADATA
python_freeathome_local-0.0.6.dist-info/WHEEL
python_freeathome_local-0.0.6.dist-info/top_level.txt
python_freeathome_local-0.0.6.dist-info/RECORD
