Metadata-Version: 2.1
Name: python_freeathome_local
Version: 0.0.6
Summary: Python Library to communicate with local Busch-Jaeger Free@Home REST API
Home-page: https://github.com/derjoerg/python_freeathome_local
Download-URL: https://github.com/derjoerg/python_freeathome_local/tarball/0.0.6
Author: Joerg Schoppet
Author-email: joerg@schoppet.de
License: MIT License
Keywords: freeathome,busch-jaeger,rest,home,automation
Platform: any
Classifier: Development Status :: 4 - Beta
Classifier: Intended Audience :: Developers
Classifier: License :: OSI Approved :: MIT License
Classifier: Operating System :: OS Independent
Classifier: Programming Language :: Python :: 3.11
Classifier: Programming Language :: Python :: 3.12
Classifier: Topic :: Home Automation
Requires-Python: >=3.11
License-File: LICENSE
Requires-Dist: aiohttp >=3.9.1
